myfuncs.py
funko-0.0.1.dist-info/LICENSE
funko-0.0.1.dist-info/METADATA
funko-0.0.1.dist-info/WHEEL
funko-0.0.1.dist-info/top_level.txt
funko-0.0.1.dist-info/RECORD
