Metadata-Version: 2.1
Name: funko
Version: 0.0.1
Summary: Myfuncolandia
Home-page: UNKNOWN
Author: 
Author-email: 
License: UNKNOWN
Platform: UNKNOWN
License-File: LICENSE
Requires-Dist: numpy (~=1.19.5)
